splearn/__init__.py
splearn/fourier.py
splearn/data/__init__.py
splearn/data/generate.py
splearn/filter/__init__.py
splearn/filter/butter.py
splearn-0.1a1.dist-info/LICENSE
splearn-0.1a1.dist-info/METADATA
splearn-0.1a1.dist-info/WHEEL
splearn-0.1a1.dist-info/top_level.txt
splearn-0.1a1.dist-info/RECORD
