Metadata-Version: 2.1
Name: splearn
Version: 0.1a1
Summary: splearn: package for signal processing and machine learning with Python.
Home-page: https://github.com/jinglescode/python-signal-processing
Author: Jingles
Author-email: jinglescode@gmail.com
License: UNKNOWN
Platform: UNKNOWN
Classifier: Programming Language :: Python :: 3
Classifier: License :: OSI Approved :: BSD License
Classifier: Operating System :: OS Independent
Requires-Python: >=3.6
